libro_flow/__init__.py
libro_flow/_version.py
libro_flow/execution_handler.py
libro_flow/libro_client.py
libro_flow/libro_execution.py
libro_flow/libro_schema_form_widget.py
libro_flow-0.1.3.dist-info/METADATA
libro_flow-0.1.3.dist-info/WHEEL
libro_flow-0.1.3.dist-info/RECORD
